libname/__init__.py
libname/hello.py
libname/hey.py
Amqizi-0.2.1.dist-info/METADATA
Amqizi-0.2.1.dist-info/WHEEL
Amqizi-0.2.1.dist-info/top_level.txt
Amqizi-0.2.1.dist-info/RECORD
